tingting/__init__.py
tingting/campaign.py
tingting/client.py
tingting/contact.py
tingting/dialer.py
tingting/endpoint.py
tingting/enums.py
tingting/survey_step.py
tingting/user.py
tingting/voice.py
tingting-1.0.1.dist-info/licenses/LICENSE
tingting-1.0.1.dist-info/METADATA
tingting-1.0.1.dist-info/WHEEL
tingting-1.0.1.dist-info/top_level.txt
tingting-1.0.1.dist-info/RECORD
