Metadata-Version: 2.4
Name: tingting
Version: 1.0.1
Summary: Python client for TingTing
Author-email: Prixa <anjelika@prixa.org>
Keywords: tingting,api,client,sdk
Classifier: Programming Language :: Python :: 3
Classifier: Operating System :: OS Independent
Classifier: Intended Audience :: Developers
Classifier: Topic :: Software Development :: Libraries :: Python Modules
Requires-Python: >=3.7
Requires-Dist: requests>=2
